infestor/__init__.py
infestor/cli.py
infestor/commit.py
infestor/config.py
infestor/errors.py
infestor/manager.py
infestor/models.py
infestor/operations.py
infestor/report.py
infestor/report.py.template
infestor/test_config.py
infestor/test_manager.py
infestor/test_operations.py
infestor/test_transformers.py
infestor/test_visitors.py
infestor/testcase.py
infestor/transformers.py
infestor/version.py
infestor/visitors.py
bugout_infestor-0.0.6.dist-info/METADATA
bugout_infestor-0.0.6.dist-info/WHEEL
bugout_infestor-0.0.6.dist-info/entry_points.txt
bugout_infestor-0.0.6.dist-info/top_level.txt
bugout_infestor-0.0.6.dist-info/RECORD
