Metadata-Version: 2.1
Name: bugout-infestor
Version: 0.0.6
Summary: Humbug Infestor: Manage Humbug reporting over your code base
Home-page: https://github.com/bugout-dev/infestor
Author: Bugout.dev
Author-email: engineering@bugout.dev
License: UNKNOWN
Platform: UNKNOWN
Classifier: Development Status :: 3 - Alpha
Classifier: Programming Language :: Python
Classifier: License :: OSI Approved :: Apache Software License
Classifier: Topic :: Software Development :: Libraries
Requires-Python: >=3.8
Requires-Dist: atomicwrites
Requires-Dist: humbug
Requires-Dist: libcst
Requires-Dist: pygit2
Requires-Dist: pydantic
Provides-Extra: dev
Requires-Dist: black ; extra == 'dev'
Requires-Dist: mypy ; extra == 'dev'
Requires-Dist: wheel ; extra == 'dev'
Requires-Dist: types-atomicwrites ; extra == 'dev'
Provides-Extra: distribute
Requires-Dist: setuptools ; extra == 'distribute'
Requires-Dist: twine ; extra == 'distribute'
Requires-Dist: wheel ; extra == 'distribute'
